magneticScattering/__init__.py
magneticScattering/dft.py
magneticScattering/examples.py
magneticScattering/holography.py
magneticScattering/plot.py
magneticScattering/scatter.py
magneticScattering/structures.py
magneticScattering/data/__init__.py
magneticScattering/data/labyrinthine.npy.gz
magneticscattering-0.2.1.dist-info/licenses/LICENSE.txt
magneticscattering-0.2.1.dist-info/METADATA
magneticscattering-0.2.1.dist-info/WHEEL
magneticscattering-0.2.1.dist-info/top_level.txt
magneticscattering-0.2.1.dist-info/RECORD
