Metadata-Version: 2.4
Name: magneticScattering
Version: 0.2.1
Summary: Simulates x-ray magnetic scattering
Author: Andreas Apseros
License-Expression: BSD-3-Clause
Project-URL: Homepage, https://github.com/apseros/magneticScattering
Project-URL: Issues, https://github.com/apseros/magneticScattering/issues
Classifier: Programming Language :: Python :: 3
Classifier: Intended Audience :: Science/Research
Classifier: Operating System :: OS Independent
Requires-Python: >=3.9
License-File: LICENSE.txt
Requires-Dist: numpy
Requires-Dist: matplotlib
Requires-Dist: magpack
Dynamic: license-file
